LICENSE.txt
MANIFEST.in
README.md
README.rst
requirements.txt
setup.py
pug/__init__.py
pug/dj/__init__.py
pug/dj/db.py
pug/dj/db_routers.py
pug/dj/explore.py
pug/dj/more_django_filters.py
pug/dj/more_django_filters_urls.py
pug/dj/more_django_viewsets.py
pug/dj/package_info.py
pug/dj/sqlserver.py
pug/dj/tests.py
pug/dj/ansi/__init__.py
pug/dj/ansi/constants.py
pug/dj/crawler/__init__.py
pug/dj/crawler/admin.py
pug/dj/crawler/models.py
pug/dj/crawler/urls.py
pug/dj/crawler/views.py
pug/dj/crawlnmine/__init__.py
pug/dj/crawlnmine/manage.py
pug/dj/crawlnmine/tests.py
pug/dj/crawlnmine/crawlnmine/__init__.py
pug/dj/crawlnmine/crawlnmine/celery.py
pug/dj/crawlnmine/crawlnmine/urls.py
pug/dj/crawlnmine/crawlnmine/wsgi.py
pug/dj/crawlnmine/crawlnmine/settings/__init__.py
pug/dj/crawlnmine/crawlnmine/settings/common.py
pug/dj/crawlnmine/crawlnmine/settings/dev.py
pug/dj/crawlnmine/crawlnmine/settings/master_common.py
pug/dj/crawlnmine/crawlnmine/settings/prod.py
pug/dj/crawlnmine/fabfile/__init__.py
pug/dj/crawlnmine/fabfile/django_fabric_aws.py
pug/dj/crawlnmine/fabfile/tasks.py
pug/dj/crawlnmine/management/__init__.py
pug/dj/crawlnmine/management/commands/__init__.py
pug/dj/crawlnmine/management/commands/create.py
pug/dj/microsoft/__init__.py
pug/dj/microsoft/constants.py
pug/dj/miner/__init__.py
pug/dj/miner/admin.py
pug/dj/miner/context_processors.py
pug/dj/miner/decorators.py
pug/dj/miner/forms.py
pug/dj/miner/model_mixin.py
pug/dj/miner/models.py
pug/dj/miner/tests.py
pug/dj/miner/urls.py
pug/dj/miner/views.py
pug/dj/miner/management/__init__.py
pug/dj/miner/management/commands/__init__.py
pug/dj/miner/management/commands/dbstats.py
pug/dj/miner/management/commands/inspect_dbs.py
pug/dj/miner/management/commands/inspectdb_1_5c2.py
pug/dj/miner/management/commands/inspectdb_1_7.py
pug/dj/miner/management/commands/inspectdb_ms.py
pug/dj/miner/management/commands/modeldb.py
pug/dj/miner/migrations/0001_initial.py
pug_dj.egg-info/PKG-INFO
pug_dj.egg-info/SOURCES.txt
pug_dj.egg-info/dependency_links.txt
pug_dj.egg-info/namespace_packages.txt
pug_dj.egg-info/requires.txt
pug_dj.egg-info/top_level.txt
