Metadata-Version: 1.1
Name: pug-dj
Version: 0.0.18
Summary: # pug-dj
Home-page: UNKNOWN
Author: Hobson <hobson@totalgood.com>
Author-email: hobson@totalgood.com
License: UNKNOWN
Download-URL: https://github.com/hobson/pug-dj/tarball/master
Keywords: django,data,web,webapp,web application,crawler,spider,science,data science,data mining
Platform: UNKNOWN
Classifier: Programming Language :: Python
Classifier: Programming Language :: Python :: 2.7
Classifier: Development Status :: 3 - Alpha
Classifier: Environment :: Other Environment
Classifier: Environment :: Console
Classifier: Intended Audience :: Developers
Classifier: License :: OSI Approved :: MIT License
Classifier: Operating System :: OS Independent
Classifier: Topic :: Software Development :: Libraries :: Python Modules
Classifier: Topic :: Scientific/Engineering :: Artificial Intelligence
Classifier: Topic :: Scientific/Engineering :: Mathematics
Classifier: Topic :: Internet :: WWW/HTTP :: Indexing/Search
